django_selectel/__init__.py
django_selectel/api.py
django_selectel/apps.py
django_selectel/models.py
django_selectel/settings.py
django_selectel/utils.py
django_selectel/storages/__init__.py
django_selectel/storages/api_storage.py
django_selectel-2.0.6.dist-info/METADATA
django_selectel-2.0.6.dist-info/WHEEL
django_selectel-2.0.6.dist-info/top_level.txt
django_selectel-2.0.6.dist-info/RECORD
