Metadata-Version: 2.1
Name: django-selectel
Version: 2.0.6
Summary: The file store in the Selectel cloud store for Django
Home-page: https://github.com/KokocGroup/django_selectel
Download-URL: https://github.com/KokocGroup/django_selectel/tarball/v2.0.6
Author: KokocGroup
Author-email: dev@kokoc.com
License: BSD
Classifier: Development Status :: 5 - Production/Stable
Classifier: Environment :: Web Environment
Classifier: Framework :: Django
Classifier: Operating System :: OS Independent
Classifier: Programming Language :: Python
Classifier: Programming Language :: Python :: 2
Classifier: Programming Language :: Python :: 2.7
Classifier: Topic :: Internet :: WWW/HTTP
Requires-Dist: requests
